Metadata-Version: 2.4
Name: mseep-yandex-tracker-mcp
Version: 0.4.2
Summary: Yandex Tracker MCP Server
Author-email: mseep <support@skydeck.ai>
Requires-Python: >=3.10
License-File: LICENSE
Requires-Dist: aiocache[redis]>=0.12.3
Requires-Dist: aiohttp>=3.11.18
Requires-Dist: mcp[cli]>=1.12.3
Requires-Dist: pydantic>=2.11.3
Requires-Dist: pydantic-settings>=2.8.1
Requires-Dist: python-dateutil>=2.9.0.post0
Requires-Dist: yandexcloud>=0.353.0
Requires-Dist: yarl>=1.20.0
Dynamic: license-file
